swh/scanner/__init__.py
swh/scanner/cli.py
swh/scanner/config.py
swh/scanner/data.py
swh/scanner/exceptions.py
swh/scanner/output.py
swh/scanner/policy.py
swh/scanner/py.typed
swh/scanner/scanner.py
swh/scanner/setup_wizard.py
swh/scanner/dashboard/__init__.py
swh/scanner/dashboard/dashboard.py
swh/scanner/dashboard/assets/bootstrap.css
swh/scanner/dashboard/assets/bootstrap.min.css
swh/scanner/dashboard/assets/favicon-16x16.png
swh/scanner/dashboard/assets/favicon-32x32.png
swh/scanner/dashboard/assets/favicon.ico
swh/scanner/dashboard/assets/swh-logo.svg
swh/scanner/dashboard/static/css/dashboard.css
swh/scanner/dashboard/static/img/favicon-16x16.png
swh/scanner/dashboard/static/img/favicon-32x32.png
swh/scanner/dashboard/static/img/favicon.ico
swh/scanner/dashboard/static/img/swh-logo.svg
swh/scanner/dashboard/templates/base.html
swh/scanner/dashboard/templates/dashboard.html
swh/scanner/dashboard/templates/results.html
swh/scanner/dashboard/templates/partials/provenance.html
swh/scanner/dashboard/templates/partials/tree.html
swh/scanner/resources/README.rst
swh/scanner/resources/gitignore/AL.gitignore
swh/scanner/resources/gitignore/Actionscript.gitignore
swh/scanner/resources/gitignore/Ada.gitignore
swh/scanner/resources/gitignore/Agda.gitignore
swh/scanner/resources/gitignore/Android.gitignore
swh/scanner/resources/gitignore/AppEngine.gitignore
swh/scanner/resources/gitignore/AppceleratorTitanium.gitignore
swh/scanner/resources/gitignore/ArchLinuxPackages.gitignore
swh/scanner/resources/gitignore/Autotools.gitignore
swh/scanner/resources/gitignore/C++.gitignore
swh/scanner/resources/gitignore/C.gitignore
swh/scanner/resources/gitignore/CFWheels.gitignore
swh/scanner/resources/gitignore/CMake.gitignore
swh/scanner/resources/gitignore/CONTRIBUTING.md
swh/scanner/resources/gitignore/CUDA.gitignore
swh/scanner/resources/gitignore/CakePHP.gitignore
swh/scanner/resources/gitignore/ChefCookbook.gitignore
swh/scanner/resources/gitignore/Clojure.gitignore
swh.scanner-0.8.2.dist-info/AUTHORS
swh.scanner-0.8.2.dist-info/LICENSE
swh.scanner-0.8.2.dist-info/METADATA
swh.scanner-0.8.2.dist-info/WHEEL
swh.scanner-0.8.2.dist-info/entry_points.txt
swh.scanner-0.8.2.dist-info/top_level.txt
swh.scanner-0.8.2.dist-info/RECORD
