Metadata-Version: 2.1
Name: swh.scanner
Version: 0.8.2
Summary: Software Heritage code scanner
Author-email: Software Heritage developers <swh-devel@inria.fr>
Project-URL: Homepage, https://gitlab.softwareheritage.org/swh/devel/swh-scanner
Project-URL: Bug Reports, https://gitlab.softwareheritage.org/swh/devel/swh-scanner/-/issues
Project-URL: Funding, https://www.softwareheritage.org/donate
Project-URL: Documentation, https://docs.softwareheritage.org/devel/swh-scanner/
Project-URL: Source, https://gitlab.softwareheritage.org/swh/devel/swh-scanner.git
Classifier: Programming Language :: Python :: 3
Classifier: Intended Audience :: Developers
Classifier: License :: OSI Approved :: GNU General Public License v3 (GPLv3)
Classifier: Operating System :: OS Independent
Classifier: Development Status :: 3 - Alpha
Requires-Python: >=3.7
License-File: LICENSE
License-File: AUTHORS
Requires-Dist: requests
Requires-Dist: ndjson
Requires-Dist: flask
Requires-Dist: importlib-metadata
Requires-Dist: swh.core >=0.3
Requires-Dist: swh.model >=6.15.0
Requires-Dist: swh.auth
Requires-Dist: swh.web.client >=0.9.0
Provides-Extra: testing
Requires-Dist: pytest >=8.1 ; extra == 'testing'
Requires-Dist: pytest-flask ; extra == 'testing'
Requires-Dist: pytest-mock ; extra == 'testing'
Requires-Dist: swh.core[testing-core] ; extra == 'testing'
Requires-Dist: swh.model[testing] ; extra == 'testing'
Requires-Dist: types-pyyaml ; extra == 'testing'
Requires-Dist: types-requests ; extra == 'testing'
Requires-Dist: bs4 ; extra == 'testing'
Requires-Dist: types-beautifulsoup4 ; extra == 'testing'
